cpdbench/CPDBench.py
cpdbench/__init__.py
cpdbench/control/CPDDatasetResult.py
cpdbench/control/CPDFullResult.py
cpdbench/control/CPDResult.py
cpdbench/control/CPDValidationResult.py
cpdbench/control/DatasetExecutor.py
cpdbench/control/ExecutionController.py
cpdbench/control/TestbenchController.py
cpdbench/control/TestrunController.py
cpdbench/control/ValidationRunController.py
cpdbench/control/__init__.py
cpdbench/dataset/CPD2DFromFileDataset.py
cpdbench/dataset/CPDDataset.py
cpdbench/dataset/CPDNdarrayDataset.py
cpdbench/dataset/__init__.py
cpdbench/examples/ExampleAlgorithms.py
cpdbench/examples/ExampleDatasets.py
cpdbench/examples/ExampleMetrics.py
cpdbench/examples/Example_Exception.py
cpdbench/examples/Example_Parallelism.py
cpdbench/examples/Example_Parameters.py
cpdbench/examples/Example_Simple.py
cpdbench/examples/Example_Validation.py
cpdbench/examples/Example_ValidationRuntime.py
cpdbench/examples/Example_VeryLargeDataset.py
cpdbench/examples/__init__.py
cpdbench/examples/configs/VeryLargeDatasetConfig.yml
cpdbench/examples/configs/parametersConfig.yml
cpdbench/examples/data/apple.npy
cpdbench/examples/data/apple_big.npy
cpdbench/examples/data/apple_medium.npy
cpdbench/examples/data/apple_small.npy
cpdbench/examples/data/apple_very_big.npy
cpdbench/examples/data/bitcoin.npy
cpdbench/examples/data/generate_very_big_numpy_file.dat.py
cpdbench/examples/performance/overhead_performance_test.py
cpdbench/exception/AlgorithmExecutionException.py
cpdbench/exception/CPDExecutionException.py
cpdbench/exception/ConfigurationException.py
cpdbench/exception/DatasetFetchException.py
cpdbench/exception/MetricExecutionException.py
cpdbench/exception/ResultSetInconsistentException.py
cpdbench/exception/UserParameterDoesNotExistException.py
cpdbench/exception/ValidationException.py
cpdbench/exception/__init__.py
cpdbench/task/AlgorithmExecutionTask.py
cpdbench/task/DatasetFetchTask.py
cpdbench/task/MetricExecutionTask.py
cpdbench/task/Task.py
cpdbench/task/TaskFactory.py
cpdbench-1.0.0.dist-info/METADATA
cpdbench-1.0.0.dist-info/WHEEL
cpdbench-1.0.0.dist-info/licenses/LICENSE
cpdbench-1.0.0.dist-info/RECORD
