Metadata-Version: 2.3
Name: cpdbench
Version: 1.0.0
Summary: A benchmarking framework to run and evaluate changepoint detection algorithms.
Project-URL: Documentation, https://github.com/Lucew/CPD-Bench#readme
Project-URL: Issues, https://github.com/Lucew/CPD-Bench/issues
Project-URL: Source, https://github.com/Lucew/CPD-Bench
Author-email: Dominik Sauerer <dominik.sauerer@gmail.com>
License-Expression: BSD-2-Clause
License-File: LICENSE
Classifier: Development Status :: 4 - Beta
Classifier: Programming Language :: Python
Classifier: Programming Language :: Python :: 3.9
Classifier: Programming Language :: Python :: Implementation :: CPython
Classifier: Programming Language :: Python :: Implementation :: PyPy
Requires-Python: >=3.9
Requires-Dist: changepoynt==0.0.7
Requires-Dist: numpy
Requires-Dist: pyyaml
Requires-Dist: tqdm
